<ns0:entry xmlns:ns0="http://www.w3.org/2005/Atom" xmlns:ns1="http://arxiv.org/schemas/atom">
    <ns0:id>http://arxiv.org/abs/2507.13347v3</ns0:id>
    <ns0:title>$π^3$: Permutation-Equivariant Visual Geometry Learning</ns0:title>
    <ns0:updated>2026-03-07T07:01:59Z</ns0:updated>
    <ns0:link href="https://arxiv.org/abs/2507.13347v3" rel="alternate" type="text/html" />
    <ns0:link href="https://arxiv.org/pdf/2507.13347v3" rel="related" type="application/pdf" title="pdf" />
    <ns0:summary>We introduce $π^3$, a feed-forward neural network that offers a novel approach to visual geometry reconstruction, breaking the reliance on a conventional fixed reference view. Previous methods often anchor their reconstructions to a designated viewpoint, an inductive bias that can lead to instability and failures if the reference is suboptimal. In contrast, $π^3$ employs a fully permutation-equivariant architecture to predict affine-invariant camera poses and scale-invariant local point maps without any reference frames. This design not only makes our model inherently robust to input ordering, but also leads to higher accuracy and performance. These advantages enable our simple and bias-free approach to achieve state-of-the-art performance on a wide range of tasks, including camera pose estimation, monocular/video depth estimation, and dense point map reconstruction. Code and models are available at https://github.com/yyfz/Pi3.</ns0:summary>
    <ns0:category term="cs.CV" scheme="http://arxiv.org/schemas/atom" />
    <ns0:published>2025-07-17T17:59:53Z</ns0:published>
    <ns1:comment>Project page: https://yyfz.github.io/pi3/</ns1:comment>
    <ns1:primary_category term="cs.CV" />
    <ns0:author>
      <ns0:name>Yifan Wang</ns0:name>
    </ns0:author>
    <ns0:author>
      <ns0:name>Jianjun Zhou</ns0:name>
    </ns0:author>
    <ns0:author>
      <ns0:name>Haoyi Zhu</ns0:name>
    </ns0:author>
    <ns0:author>
      <ns0:name>Wenzheng Chang</ns0:name>
    </ns0:author>
    <ns0:author>
      <ns0:name>Yang Zhou</ns0:name>
    </ns0:author>
    <ns0:author>
      <ns0:name>Zizun Li</ns0:name>
    </ns0:author>
    <ns0:author>
      <ns0:name>Junyi Chen</ns0:name>
    </ns0:author>
    <ns0:author>
      <ns0:name>Jiangmiao Pang</ns0:name>
    </ns0:author>
    <ns0:author>
      <ns0:name>Chunhua Shen</ns0:name>
    </ns0:author>
    <ns0:author>
      <ns0:name>Tong He</ns0:name>
    </ns0:author>
  </ns0:entry>
  