{
 "paperId": "ed8a0328afaed8da8c7f84196208dd7cf449ccd5",
 "externalIds": {
  "ArXiv": "2503.07507",
  "DBLP": "journals/corr/abs-2503-07507",
  "DOI": "10.48550/arXiv.2503.07507",
  "CorpusId": 276928863
 },
 "publicationVenue": {
  "id": "1901e811-ee72-4b20-8f7e-de08cd395a10",
  "name": "arXiv.org",
  "alternate_names": [
   "ArXiv"
  ],
  "issn": "2331-8422",
  "url": "https://arxiv.org"
 },
 "title": "PE3R: Perception-Efficient 3D Reconstruction",
 "venue": "arXiv.org",
 "year": 2025,
 "publicationTypes": [
  "JournalArticle"
 ],
 "journal": {
  "name": "ArXiv",
  "volume": "abs/2503.07507"
 },
 "authors": [
  {
   "authorId": "2219715847",
   "name": "Jie Hu"
  },
  {
   "authorId": "2296095520",
   "name": "Shizun Wang"
  },
  {
   "authorId": "2107980712",
   "name": "Xinchao Wang"
  }
 ]
}