{
 "arxiv_id": "2604.15284",
 "authors": [
  "Roni Itkin",
  "Noam Issachar",
  "Yehonatan Keypur",
  "Xingyu Chen",
  "Anpei Chen",
  "Sagie Benaim"
 ],
 "award": "",
 "category": "gaussian-splatting",
 "file": "docs/gaussian-splatting/globalsplat.md",
 "institution": "The Hebrew University of Jerusalem; Westlake University",
 "links": {
  "paper": "https://arxiv.org/abs/2604.15284",
  "project": "https://r-itk.github.io/globalsplat/"
 },
 "name": "GlobalSplat",
 "slug": "globalsplat",
 "tables": [
  {
   "header": [
    "Method",
    "PSNR ↑",
    "SSIM ↑",
    "LPIPS ↓",
    "#G(K) ↓"
   ],
   "rows": [
    [
     "LVSM (non-GS)",
     "27.24",
     "0.874",
     "0.112",
     "–"
    ],
    [
     "NoPoSplat",
     "21.24",
     "0.664",
     "0.200",
     "1204"
    ],
    [
     "AnySplat",
     "24.11",
     "0.838",
     "0.198",
     "2636"
    ],
    [
     "EcoSplat",
     "24.72",
     "0.822",
     "0.183",
     "78"
    ],
    [
     "DepthSplat",
     "19.66",
     "0.743",
     "0.239",
     "1572"
    ],
    [
     "GGN",
     "18.50",
     "0.682",
     "0.299",
     "385"
    ],
    [
     "Zpressor (6 views)",
     "**28.51**",
     "**0.911**",
     "**0.097**",
     "393"
    ],
    [
     "Zpressor (3 views)",
     "23.65",
     "0.846",
     "0.157",
     "197"
    ],
    [
     "C3G",
     "23.80",
     "0.747",
     "0.198",
     "2"
    ],
    [
     "GlobalSplat-2K (Ours)",
     "26.84",
     "0.838",
     "0.198",
     "2"
    ],
    [
     "GlobalSplat-16K (Ours)",
     "28.53",
     "0.883",
     "0.140",
     "16"
    ],
    [
     "GlobalSplat-32K (Ours)",
     "29.48",
     "0.901",
     "0.122",
     "32"
    ]
   ]
  },
  {
   "header": [
    "Method",
    "PSNR ↑",
    "SSIM ↑",
    "LPIPS ↓",
    "#G(K) ↓"
   ],
   "rows": [
    [
     "LVSM (non-GS)",
     "28.29",
     "0.826",
     "0.161",
     "–"
    ],
    [
     "DepthSplat",
     "20.15",
     "0.711",
     "0.258",
     "1572"
    ],
    [
     "GGN",
     "20.90",
     "0.657",
     "0.314",
     "396"
    ],
    [
     "Zpressor",
     "**28.53**",
     "**0.860**",
     "**0.138**",
     "393"
    ],
    [
     "C3G",
     "22.24",
     "0.598",
     "0.331",
     "2"
    ],
    [
     "GlobalSplat-16K (Ours)",
     "28.03",
     "0.813",
     "0.207",
     "16"
    ]
   ]
  },
  {
   "header": [
    "Metric",
    "LVSM",
    "DepthSplat",
    "Zpressor",
    "C3G",
    "GGN",
    "Ours16K"
   ],
   "rows": [
    [
     "Peak Mem (GB)",
     "4.60",
     "29.84",
     "3.70",
     "6.04",
     "25.08",
     "**1.79**"
    ],
    [
     "Inf. Time (ms)",
     "940.00",
     "669.50",
     "194.20",
     "387.14",
     "1800.64",
     "**77.88**"
    ],
    [
     "Size on Disk (MB)",
     "–",
     "534",
     "134",
     "0.1",
     "174",
     "3.8"
    ]
   ]
  },
  {
   "header": [
    "Variant",
    "PSNR ↑",
    "SSIM ↑",
    "LPIPS ↓"
   ],
   "rows": [
    [
     "Ours (full)",
     "**28.57**",
     "**0.885**",
     "**0.139**"
    ],
    [
     "Plücker only",
     "28.30",
     "0.880",
     "0.140"
    ],
    [
     "w/o consistency loss",
     "28.15",
     "0.876",
     "0.143"
    ],
    [
     "Single-stream",
     "28.02",
     "0.873",
     "0.151"
    ],
    [
     "Direct full-capacity prediction",
     "27.69",
     "0.867",
     "0.150"
    ]
   ]
  },
  {
   "header": [
    "Total #G",
    "#Latents",
    "Splats/Token",
    "PSNR ↑",
    "SSIM ↑",
    "LPIPS ↓"
   ],
   "rows": [
    [
     "2,048",
     "256",
     "8",
     "25.25",
     "0.785",
     "0.250"
    ],
    [
     "2,048",
     "2,048",
     "1",
     "26.83",
     "0.838",
     "0.198"
    ],
    [
     "16,384",
     "2,048",
     "8",
     "28.57",
     "0.885",
     "0.138"
    ],
    [
     "32,768",
     "2,048",
     "16",
     "28.58",
     "0.884",
     "0.135"
    ],
    [
     "32,768",
     "4,096",
     "8",
     "29.54",
     "0.903",
     "0.121"
    ]
   ]
  }
 ],
 "title": "GlobalSplat: Efficient Feed-Forward 3D Gaussian Splatting via Global Scene Tokens (arXiv preprint (2026-04))",
 "venue": "arXiv preprint (2026-04)",
 "verification": "PREPRINT (2026-07-21)"
}