{
 "arxiv_id": "2601.17866",
 "authors": [
  "Yoonwoo Jeong",
  "Cheng Sun",
  "Yu-Chiang Frank Wang",
  "Minsu Cho",
  "Jaesung Choe"
 ],
 "award": "",
 "category": "understanding",
 "file": "docs/understanding/mv-sam.md",
 "institution": "NVIDIA, POSTECH",
 "links": {
  "paper": "https://arxiv.org/abs/2601.17866"
 },
 "name": "MV-SAM",
 "slug": "mv-sam",
 "tables": [
  {
   "header": [
    "Dataset",
    "SAM2-Video (Video)",
    "MV-SAM (Video)",
    "SAM2-Video (MV-Images)",
    "MV-SAM (MV-Images)"
   ],
   "rows": [
    [
     "ScanNet++",
     "46.1 / 61.4",
     "**48.9 / 63.5**",
     "47.5 / 62.8",
     "**49.1 / 62.9**"
    ],
    [
     "uCo3D",
     "81.9 / 91.3",
     "**87.7 / 95.0**",
     "83.2 / 91.9",
     "**87.4 / 95.1**"
    ],
    [
     "DL3DV",
     "67.3 / 82.9",
     "**75.1 / 91.8**",
     "64.2 / 78.6",
     "**75.0 / 92.0**"
    ],
    [
     "Average",
     "65.1 / 78.5",
     "**70.6 / 83.4**",
     "65.0 / 77.8",
     "**70.5 / 83.3**"
    ]
   ]
  },
  {
   "header": [
    "Category",
    "Method",
    "NVOS mIoU / mAcc",
    "SPIn-NeRF mIoU / mAcc"
   ],
   "rows": [
    [
     "per-scene opt.",
     "SPIn-NeRF",
     "- / -",
     "90.7 / 98.8"
    ],
    [
     "per-scene opt.",
     "SA3D",
     "91.1 / 98.4",
     "92.4 / 98.8"
    ],
    [
     "per-scene opt.",
     "SAGA",
     "92.6 / 98.6",
     "93.7 / 99.2"
    ],
    [
     "per-scene opt.",
     "SA3D-GS",
     "92.7 / 98.5",
     "93.4 / 99.1"
    ],
    [
     "per-scene opt.",
     "OmniSeg3D",
     "92.8 / 98.6",
     "94.5 / 99.3"
    ],
    [
     "generalization",
     "SAM2-Video",
     "88.7 / 94.6",
     "86.6 / 93.6"
    ],
    [
     "generalization",
     "MV-SAM",
     "92.1 / 97.5",
     "92.9 / 97.1"
    ]
   ]
  },
  {
   "header": [
    "CP",
    "PE",
    "Attn",
    "mIoU / mAcc"
   ],
   "rows": [
    [
     "",
     "3D PE",
     "single-view",
     "44.5 / 61.1"
    ],
    [
     "✓",
     "No PE",
     "single-view",
     "10.9 / 52.7"
    ],
    [
     "✓",
     "No PE",
     "full-view",
     "25.6 / 57.8"
    ],
    [
     "✓",
     "2D PE",
     "single-view",
     "18.3 / 53.6"
    ],
    [
     "✓",
     "2D PE",
     "full-view",
     "26.6 / 59.5"
    ],
    [
     "✓",
     "3D PE",
     "full-view",
     "45.8 / 62.2"
    ],
    [
     "✓",
     "3D PE",
     "single-view",
     "**52.2 / 66.7**"
    ]
   ]
  },
  {
   "header": [
    "Train → Eval",
    "mIoU / mAcc"
   ],
   "rows": [
    [
     "ScanNet++ → ScanNet++",
     "0.510 / 0.694"
    ],
    [
     "uCo3D → ScanNet++",
     "0.194 / 0.251"
    ],
    [
     "SA-1B → ScanNet++",
     "0.489 / 0.635"
    ],
    [
     "uCo3D → uCo3D",
     "0.910 / 0.965"
    ],
    [
     "ScanNet++ → uCo3D",
     "0.322 / 0.517"
    ],
    [
     "SA-1B → uCo3D",
     "0.877 / 0.950"
    ]
   ]
  },
  {
   "header": [
    "VGM",
    "mIoU / mAcc"
   ],
   "rows": [
    [
     "VGGT",
     "61.1 / 90.4"
    ],
    [
     "WorldMirror",
     "74.3 / 92.6"
    ],
    [
     "π³",
     "75.1 / 91.8"
    ]
   ]
  },
  {
   "header": [
    "Method",
    "Pre-processing",
    "Inference",
    "# params",
    "FLOPs (TFLOPs)"
   ],
   "rows": [
    [
     "SAGA",
     "31 min",
     "528 ms",
     "–",
     "–"
    ],
    [
     "OmniSeg3D",
     "37 min",
     "463 ms",
     "–",
     "–"
    ],
    [
     "SAM2-Video",
     "3.2 s",
     "4.8 s",
     "12.3M",
     "16.8"
    ],
    [
     "MV-SAM",
     "5.1 s",
     "1.1 s",
     "4.1M",
     "44.6"
    ]
   ]
  }
 ],
 "title": "MV-SAM: Multi-view Promptable Segmentation using Pointmap Guidance (arXiv preprint 2026-01)",
 "venue": "arXiv preprint (2026-01)",
 "verification": "PREPRINT (2026-07-21)"
}