{
 "arxiv_id": "2604.00548",
 "authors": [
  "Youyu Chen",
  "Junjun Jiang",
  "Yueru Luo",
  "Kui Jiang",
  "Xianming Liu",
  "Xu Yan",
  "Dave Zhenyu Chen"
 ],
 "award": "",
 "category": "reconstruction",
 "file": "docs/reconstruction/reliev3r.md",
 "institution": "Harbin Institute of Technology, Huawei, The Chinese University of Hong Kong, Shenzhen",
 "links": {
  "paper": "https://arxiv.org/abs/2604.00548"
 },
 "name": "Reliev3R",
 "slug": "reliev3r",
 "tables": [
  {
   "header": [
    "Method",
    "DL3DV-10K",
    "MVG Ann.",
    "Point Map rel ↓",
    "Point Map τ ↑",
    "Pose ATE ↓",
    "Pose AUC ↑",
    "Depth rel ↓",
    "Depth τ ↑"
   ],
   "rows": [
    [
     "Map-Anything",
     "Yes",
     "w",
     "0.051",
     "0.911",
     "0.004",
     "87.088",
     "0.045",
     "0.896"
    ],
    [
     "π³",
     "No",
     "w",
     "0.056",
     "**0.927**",
     "**0.003**",
     "92.746",
     "0.054",
     "**0.916**"
    ],
    [
     "VGGT",
     "Yes",
     "w",
     "0.061",
     "0.905",
     "**0.003**",
     "**94.795**",
     "0.059",
     "0.899"
    ],
    [
     "CUT3R",
     "Yes",
     "w",
     "0.073",
     "0.815",
     "0.005",
     "89.432",
     "0.072",
     "0.801"
    ],
    [
     "π³†",
     "Alone",
     "w",
     "0.057",
     "0.897",
     "0.013",
     "63.314",
     "0.047",
     "0.890"
    ],
    [
     "MVDUSt3R",
     "No",
     "w",
     "0.593",
     "0.233",
     "0.458",
     "2.529",
     "0.690",
     "0.134"
    ],
    [
     "FLARE",
     "Yes",
     "w",
     "0.134",
     "0.771",
     "0.338",
     "80.905",
     "0.376",
     "0.302"
    ],
    [
     "AnyCam",
     "No",
     "w/o",
     "0.262",
     "0.490",
     "0.023",
     "29.527",
     "0.181",
     "0.400"
    ],
    [
     "**Reliev3R**",
     "Alone",
     "**w/o**",
     "0.122",
     "0.663",
     "0.018",
     "49.426",
     "0.115",
     "0.657"
    ]
   ]
  },
  {
   "header": [
    "Method",
    "Point Map rel ↓",
    "Point Map τ ↑",
    "Pose ATE ↓",
    "Pose AUC ↑",
    "Depth rel ↓",
    "Depth τ ↑"
   ],
   "rows": [
    [
     "π³",
     "**0.027**",
     "**0.972**",
     "**0.002**",
     "**86.941**",
     "**0.027**",
     "**0.970**"
    ],
    [
     "π³†",
     "0.232",
     "0.678",
     "**0.028**",
     "17.789",
     "0.220",
     "0.171"
    ],
    [
     "AnyCam",
     "0.438",
     "0.448",
     "0.084",
     "15.376",
     "0.286",
     "0.095"
    ],
    [
     "**Reliev3R**",
     "0.172",
     "0.594",
     "0.030",
     "15.711",
     "0.124",
     "0.583"
    ]
   ]
  },
  {
   "header": [
    "Method",
    "Point Map rel ↓",
    "Point Map τ ↑",
    "Pose ATE ↓",
    "Pose AUC ↑",
    "Depth rel ↓",
    "Depth τ ↑"
   ],
   "rows": [
    [
     "RayZer",
     "×",
     "×",
     "0.786",
     "0.362",
     "×",
     "×"
    ],
    [
     "Synth Fully-Sup.",
     "0.277",
     "0.475",
     "0.042",
     "17.075",
     "0.208",
     "0.357"
    ],
    [
     "**+Reliev3R**",
     "**0.137**",
     "**0.667**",
     "**0.033**",
     "**34.240**",
     "**0.106**",
     "**0.679**"
    ]
   ]
  },
  {
   "header": [
    "α",
    "Point Map rel ↓",
    "Point Map τ ↑",
    "ATE ↓",
    "AUC ↑",
    "Depth rel ↓",
    "Depth τ ↑"
   ],
   "rows": [
    [
     "α = 0.2",
     "0.143",
     "0.607",
     "0.022",
     "42.116",
     "0.137",
     "0.606"
    ],
    [
     "α = 0.5",
     "0.137",
     "0.626",
     "0.023",
     "46.703",
     "0.129",
     "0.628"
    ],
    [
     "**α = 1.0**",
     "**0.122**",
     "**0.663**",
     "**0.018**",
     "**49.426**",
     "**0.115**",
     "**0.657**"
    ],
    [
     "α = 2.0",
     "0.127",
     "0.651",
     "0.020",
     "48.566",
     "0.121",
     "0.647"
    ]
   ]
  }
 ],
 "title": "Reliev3R: Relieving Feed-forward 3D Reconstruction from Multi-View Geometric Annotations (CVPR 2026)",
 "venue": "CVPR 2026",
 "verification": "CONFIRMED (2026-07-20)"
}