{
 "arxiv_id": "2605.17942",
 "authors": [
  "Xiang Yang",
  "Yongli Wang",
  "HaiFeng Li",
  "Yunsheng Zhang"
 ],
 "award": "",
 "category": "foundation",
 "file": "docs/foundation/uavff3d.md",
 "institution": "School of Geosciences and Info-Physics, Central South University, Changsha, China",
 "links": {
  "code": "https://github.com/yanxian-ll/UAVFF3D",
  "paper": "https://arxiv.org/abs/2605.17942"
 },
 "name": "UAVFF3D",
 "slug": "uavff3d",
 "tables": [
  {
   "header": [
    "Component",
    "Source",
    "Scenes",
    "Images"
   ],
   "rows": [
    [
     "UAVFF3D-Real",
     "Real",
     "107",
     "170k"
    ],
    [
     "UAVFF3D-Syn",
     "Synthetic",
     "291",
     "370k"
    ],
    [
     "UAVFF3D-FA",
     "Synthetic",
     "32",
     "19k"
    ]
   ]
  },
  {
   "header": [
    "Dataset",
    "CD-S ↓",
    "ATE-S ↓",
    "ATE-I ↓",
    "Gap ↓"
   ],
   "rows": [
    [
     "UseGeo",
     "1.61",
     "8.32",
     "3.36",
     "4.96"
    ],
    [
     "UrbanScene3D",
     "4.75",
     "77.78",
     "44.51",
     "33.27"
    ],
    [
     "UAVFF3D-Real",
     "3.38",
     "89.45",
     "47.21",
     "42.24"
    ],
    [
     "UAVFF3D-FA",
     "1.04",
     "41.62",
     "1.11",
     "40.52"
    ],
    [
     "Average",
     "2.70",
     "54.29",
     "24.05",
     "30.25"
    ]
   ]
  },
  {
   "header": [
    "Model",
    "AbsRel ↓",
    "Ray ↓",
    "CD ↓",
    "ATE ↓",
    "Rot. ↓"
   ],
   "rows": [
    [
     "VGGT",
     "0.042",
     "6.23",
     "2.70",
     "54.29",
     "11.60"
    ],
    [
     "Pi3",
     "0.036",
     "8.67",
     "2.86",
     "60.39",
     "11.41"
    ],
    [
     "MapAnything",
     "0.044",
     "6.00",
     "2.90",
     "57.50",
     "13.33"
    ],
    [
     "Pi3X",
     "0.035",
     "7.73",
     "2.24",
     "56.19",
     "11.72"
    ],
    [
     "DA3",
     "0.037",
     "6.58",
     "2.94",
     "56.21",
     "14.79"
    ],
    [
     "VGGT-FT",
     "0.028",
     "1.97",
     "1.59",
     "20.57",
     "3.96"
    ],
    [
     "Pi3-FT",
     "0.026",
     "1.37",
     "1.77",
     "14.52",
     "3.07"
    ],
    [
     "Mapa-FT",
     "0.037",
     "2.51",
     "1.91",
     "29.08",
     "6.10"
    ],
    [
     "Pi3X-FT",
     "0.026",
     "1.87",
     "1.44",
     "18.70",
     "3.40"
    ]
   ]
  },
  {
   "header": [
    "Model",
    "CD Oblique ↓",
    "CD Nadir ↓",
    "CD Gap ↓",
    "Rot Oblique ↓",
    "Rot Nadir ↓",
    "Rot Gap ↓"
   ],
   "rows": [
    [
     "VGGT",
     "5.42",
     "2.02",
     "3.40",
     "31.89",
     "6.32",
     "25.57"
    ],
    [
     "MapAnything",
     "6.51",
     "1.79",
     "4.72",
     "39.02",
     "5.12",
     "33.90"
    ],
    [
     "Pi3",
     "5.80",
     "2.29",
     "3.50",
     "33.00",
     "6.86",
     "26.13"
    ],
    [
     "Pi3X",
     "5.60",
     "1.89",
     "3.71",
     "35.89",
     "10.11",
     "25.78"
    ],
    [
     "DA3",
     "5.84",
     "2.05",
     "3.79",
     "32.95",
     "10.81",
     "22.14"
    ],
    [
     "VGGT-FT",
     "2.86",
     "1.19",
     "1.68",
     "7.79",
     "3.07",
     "4.73"
    ],
    [
     "Pi3-FT",
     "2.89",
     "1.49",
     "1.40",
     "5.31",
     "2.88",
     "2.43"
    ],
    [
     "Mapa-FT",
     "3.67",
     "1.23",
     "2.44",
     "13.06",
     "3.64",
     "9.43"
    ],
    [
     "Pi3X-FT",
     "2.53",
     "1.10",
     "1.43",
     "6.29",
     "2.95",
     "3.35"
    ]
   ]
  },
  {
   "header": [
    "Model",
    "AbsRel ↓",
    "Ray ↓",
    "CD ↓",
    "ATE ↓",
    "Rot. ↓"
   ],
   "rows": [
    [
     "Pi3",
     "0.036",
     "8.67",
     "2.86",
     "60.39",
     "11.41"
    ],
    [
     "Pi3-FT-Public",
     "0.032",
     "5.59",
     "1.81",
     "46.74",
     "8.76"
    ],
    [
     "Pi3-FT-Syn",
     "0.032",
     "2.36",
     "1.65",
     "25.80",
     "5.31"
    ],
    [
     "Pi3-FT-Real",
     "0.023",
     "1.73",
     "2.15",
     "16.55",
     "2.97"
    ],
    [
     "Pi3-FT-Full",
     "0.026",
     "1.37",
     "1.77",
     "14.52",
     "3.07"
    ],
    [
     "MapAnything",
     "0.044",
     "6.00",
     "2.90",
     "57.50",
     "13.33"
    ],
    [
     "Mapa-FT-Public",
     "0.044",
     "5.39",
     "3.33",
     "55.54",
     "13.21"
    ],
    [
     "Mapa-FT-Syn",
     "0.052",
     "3.28",
     "2.64",
     "51.10",
     "11.94"
    ],
    [
     "Mapa-FT-Real",
     "0.041",
     "3.16",
     "2.45",
     "30.55",
     "6.25"
    ],
    [
     "Mapa-FT-Full",
     "0.037",
     "2.51",
     "1.91",
     "29.08",
     "6.10"
    ]
   ]
  },
  {
   "header": [
    "Model",
    "Input",
    "AbsRel ↓",
    "Ray ↓",
    "CD ↓",
    "ATE ↓",
    "Rot. ↓"
   ],
   "rows": [
    [
     "Mapa-FT",
     "RGB",
     "0.037",
     "2.51",
     "1.91",
     "29.08",
     "6.10"
    ],
    [
     "Mapa-FT",
     "C",
     "0.033",
     "0.38",
     "1.86",
     "15.86",
     "5.55"
    ],
    [
     "Mapa-FT",
     "P",
     "0.025",
     "2.38",
     "1.35",
     "17.61",
     "1.61"
    ],
    [
     "Mapa-FT",
     "CP",
     "0.021",
     "0.30",
     "1.14",
     "3.43",
     "1.06"
    ],
    [
     "Pi3X-FT",
     "RGB",
     "0.026",
     "1.87",
     "1.44",
     "18.70",
     "3.40"
    ],
    [
     "Pi3X-FT",
     "C",
     "0.020",
     "0.25",
     "1.63",
     "8.13",
     "3.14"
    ],
    [
     "Pi3X-FT",
     "P",
     "0.021",
     "1.93",
     "1.77",
     "16.50",
     "1.98"
    ],
    [
     "Pi3X-FT",
     "CP",
     "0.018",
     "0.26",
     "1.89",
     "4.80",
     "1.62"
    ]
   ]
  }
 ],
 "title": "UAVFF3D: A Geometry-Aware Benchmark for Feed-Forward UAV 3D Reconstruction (arXiv preprint 2026-05)",
 "venue": "arXiv preprint (2026-05)",
 "verification": "PREPRINT (2026-07-21)"
}